gifpgn/__init__.py
gifpgn/_types.py
gifpgn/components.py
gifpgn/exceptions.py
gifpgn/geometry.py
gifpgn/gifpgn.py
gifpgn/utils.py
gifpgn/assets/nags/blunder.png
gifpgn/assets/nags/inaccuracy.png
gifpgn/assets/nags/mistake.png
gifpgn/assets/pieces/alpha/bb.png
gifpgn/assets/pieces/alpha/bk.png
gifpgn/assets/pieces/alpha/bn.png
gifpgn/assets/pieces/alpha/bp.png
gifpgn/assets/pieces/alpha/bq.png
gifpgn/assets/pieces/alpha/br.png
gifpgn/assets/pieces/alpha/wb.png
gifpgn/assets/pieces/alpha/wk.png
gifpgn/assets/pieces/alpha/wn.png
gifpgn/assets/pieces/alpha/wp.png
gifpgn/assets/pieces/alpha/wq.png
gifpgn/assets/pieces/alpha/wr.png
gifpgn/assets/pieces/cases/bb.png
gifpgn/assets/pieces/cases/bk.png
gifpgn/assets/pieces/cases/bn.png
gifpgn/assets/pieces/cases/bp.png
gifpgn/assets/pieces/cases/bq.png
gifpgn/assets/pieces/cases/br.png
gifpgn/assets/pieces/cases/wb.png
gifpgn/assets/pieces/cases/wk.png
gifpgn/assets/pieces/cases/wn.png
gifpgn/assets/pieces/cases/wp.png
gifpgn/assets/pieces/cases/wq.png
gifpgn/assets/pieces/cases/wr.png
gifpgn/assets/pieces/maya/bb.png
gifpgn/assets/pieces/maya/bk.png
gifpgn/assets/pieces/maya/bn.png
gifpgn/assets/pieces/maya/bp.png
gifpgn/assets/pieces/maya/bq.png
gifpgn/assets/pieces/maya/br.png
gifpgn/assets/pieces/maya/wb.png
gifpgn/assets/pieces/maya/wk.png
gifpgn/assets/pieces/maya/wn.png
gifpgn/assets/pieces/maya/wp.png
gifpgn/assets/pieces/maya/wq.png
gifpgn/assets/pieces/maya/wr.png
gifpgn/assets/pieces/regular/bb.png
gifpgn/assets/pieces/regular/bk.png
gifpgn/assets/pieces/regular/bn.png
gifpgn/assets/pieces/regular/bp.png
gifpgn/assets/pieces/regular/bq.png
gifpgn/assets/pieces/regular/br.png
gifpgn/assets/pieces/regular/wb.png
gifpgn/assets/pieces/regular/wk.png
gifpgn/assets/pieces/regular/wn.png
gifpgn/assets/pieces/regular/wp.png
gifpgn/assets/pieces/regular/wq.png
gifpgn/assets/pieces/regular/wr.png
gifpgn/fonts/Carlito-Regular.ttf
gifpgn-1.1.1.dist-info/LICENSE
gifpgn-1.1.1.dist-info/METADATA
gifpgn-1.1.1.dist-info/WHEEL
gifpgn-1.1.1.dist-info/top_level.txt
gifpgn-1.1.1.dist-info/RECORD
