Metadata-Version: 2.2
Name: gifpgn
Version: 1.1.1
Summary: Chess GIF Generator for Python
Author-email: Matthew Hambly <gifpgn@quickmind.co.uk>
License: GPL-3.0-or-later
Project-URL: Homepage, http://github.com/prozn/gifpgn
Project-URL: Documentation, http://gifpgn.readthedocs.io
Keywords: chess,pgn,uci,analysis,stockfish,gif,acpl
Classifier: Development Status :: 5 - Production/Stable
Classifier: Intended Audience :: Developers
Classifier: Typing :: Typed
Classifier: Topic :: Games/Entertainment :: Board Games
Classifier: Topic :: Games/Entertainment :: Real Time Strategy
Classifier: Topic :: Software Development :: Libraries :: Python Modules
Classifier: License :: OSI Approved :: GNU General Public License v3 or later (GPLv3+)
Classifier: Programming Language :: Python :: 3 :: Only
Classifier: Programming Language :: Python :: 3.10
Classifier: Programming Language :: Python :: 3.11
Classifier: Programming Language :: Python :: 3.12
Requires-Python: >=3.10
License-File: LICENSE
Requires-Dist: pillow==11.1.0
Requires-Dist: chess==1.11.1
